redbeanpython/__init__.py
redbeanpython/bean/__init__.py
redbeanpython/bean/bean.py
redbeanpython/bean/beans.py
redbeanpython/bean/id.py
redbeanpython/bean/validator.py
redbeanpython/cli/__init__.py
redbeanpython/cli/cli.py
redbeanpython/config.py
redbeanpython/const.py
redbeanpython/errors.py
redbeanpython/facade.py
redbeanpython/model/__init__.py
redbeanpython/model/model.py
redbeanpython/model/models_creator.py
redbeanpython/py.typed
redbeanpython/redbean.py
redbeanpython/structure/__init__.py
redbeanpython/structure/column_type.py
redbeanpython/structure/db_structure.py
redbeanpython/structure/supported_types.py
redbeanpython/structure/table.py
redbeanpython/structure/type.py
redbeanpython/templates/alembic.ini.mako
redbeanpython/templates/env.py.template
redbeanpython/templates/env.sqlite.py.template
redbeanpython/templates/model.py.mako
redbeanpython/templates/script.py.mako.template
redbeanpython-1.0.2.dist-info/LICENSE
redbeanpython-1.0.2.dist-info/METADATA
redbeanpython-1.0.2.dist-info/WHEEL
redbeanpython-1.0.2.dist-info/entry_points.txt
redbeanpython-1.0.2.dist-info/RECORD
