Metadata-Version: 2.1
Name: redbeanpython
Version: 1.0.2
Summary: RedBeanPython ORM
License: MIT
Author: Adam Puza
Author-email: adampuza@redbeanpython.org
Requires-Python: >=3.11
Classifier: License :: OSI Approved :: MIT License
Classifier: Operating System :: OS Independent
Classifier: Programming Language :: Python
Classifier: Programming Language :: Python :: 3
Classifier: Programming Language :: Python :: 3.11
Classifier: Programming Language :: Python :: 3.12
Classifier: Topic :: Database :: Front-Ends
Requires-Dist: SQLAlchemy (>=2.0.0)
Requires-Dist: alembic (>=1.8.0)
Project-URL: Changelog, https://redbeanpython.org/changelog/
Project-URL: Documentation, https://redbeanpython.org/
Project-URL: Homepage, https://redbeanpython.org/
Project-URL: Issue Tracker, https://github.com/adamhmetal/redbeanpython/issues
Project-URL: Source Code, https://github.com/adamhmetal/redbeanpython
